timey.py
src/timey_kaligraphy247/__init__.py
timey_terminal-0.2.0.dist-info/METADATA
timey_terminal-0.2.0.dist-info/WHEEL
timey_terminal-0.2.0.dist-info/licenses/LICENSE.txt
timey_terminal-0.2.0.dist-info/RECORD
