Metadata-Version: 2.1
Name: timey_terminal
Version: 0.2.0
Summary: Prints text to terminal at timely intervals. Can replace the print function
Project-URL: Homepage, https://github.com/Kaligraphy247/timey
Project-URL: Bug Tracker, https://github.com/Kaligraphy247/timey/issues
Author-email: James ? <james.ononogbu@iubh.de>
License-File: LICENSE.txt
Classifier: License :: OSI Approved :: GNU General Public License v3 (GPLv3)
Classifier: Operating System :: OS Independent
Classifier: Programming Language :: Python :: 3
Requires-Python: >=3
